<?xml version="1.0" encoding="utf-8" ?><dwsync><file name="ajax.php" server="Macintosh HD/Applications/MAMP/htdocs/Shubiri/" local="3556264764" remote="3556264764" Dst="-1" /><file name="caricamento.php" server="Macintosh HD/Applications/MAMP/htdocs/Shubiri/" local="3556780253" remote="3556780253" Dst="-1" /><file name="forms_aggiungi.php" server="Macintosh HD/Applications/MAMP/htdocs/Shubiri/" local="3556780018" remote="3556780018" Dst="-1" /><file name="forms_modifica.php" server="Macintosh HD/Applications/MAMP/htdocs/Shubiri/" local="3556781295" remote="3556781295" Dst="-1" /><file name="funzioni.php" server="Macintosh HD/Applications/MAMP/htdocs/Shubiri/" local="3556782982" remote="3556782982" Dst="-1" /><file name="htaccess.php" server="Macintosh HD/Applications/MAMP/htdocs/Shubiri/" local="3556786321" remote="3556786321" Dst="-1" /><file name="htaccess.php" server="Macintosh HD/Applications/MAMP/htdocs/blancdesir/" local="3556793518" remote="3556793518" Dst="-1" /><file name="ajax.php" server="Macintosh HD/Applications/MAMP/htdocs/archeproject/" local="3561642770" remote="3561642770" Dst="-1" /><file name="caricamento.php" server="Macintosh HD/Applications/MAMP/htdocs/archeproject/" local="3560076378" remote="3560076378" Dst="-1" /><file name="forms_aggiungi.php" server="Macintosh HD/Applications/MAMP/htdocs/archeproject/" local="3561633584" remote="3561633584" Dst="-1" /><file name="forms_modifica.php" server="Macintosh HD/Applications/MAMP/htdocs/archeproject/" local="3560486712" remote="3560486712" Dst="-1" /><file name="funzioni.php" server="Macintosh HD/Applications/MAMP/htdocs/archeproject/" local="3561445671" remote="3561445671" Dst="-1" /><file name="htaccess.php" server="Macintosh HD/Applications/MAMP/htdocs/archeproject/" local="3560076378" remote="3560076378" Dst="-1" /><file name=".DS_Store" server="Macintosh HD/Applications/MAMP/htdocs/archeproject/" local="3556791680" remote="3556791680" Dst="-1" /></dwsync>